zaim_sqlite/__init__.py
zaim_sqlite/__main__.py
zaim_sqlite/lib/__init__.py
zaim_sqlite/lib/logger.py
zaim_sqlite/lib/sql.py
zaim_sqlite/lib/zaim.py
zaim_sqlite/model/__init__.py
zaim_sqlite/model/account.py
zaim_sqlite/model/base.py
zaim_sqlite/model/category.py
zaim_sqlite/model/genre.py
zaim_sqlite/model/mode.py
zaim_sqlite/model/money.py
zaim_sqlite/model/place.py
zaim_sqlite/query/money.sql
zaim_sqlite-0.2.5.dist-info/METADATA
zaim_sqlite-0.2.5.dist-info/WHEEL
zaim_sqlite-0.2.5.dist-info/entry_points.txt
zaim_sqlite-0.2.5.dist-info/licenses/LICENSE
zaim_sqlite-0.2.5.dist-info/RECORD
