Metadata-Version: 2.3
Name: zaim-sqlite
Version: 0.2.5
Summary: ZaimのデータをSQLite DBに格納するPythonパッケージ
Project-URL: Homepage, https://github.com/ryohidaka/zaim-sqlite
Project-URL: Repository, https://github.com/ryohidaka/zaim-sqlite
Project-URL: Issues, https://github.com/ryohidaka/zaim-sqlite/issues
Project-URL: Changelog, https://github.com/ryohidaka/blob/main/zaim-sqlite/CHANGELOG.md
Author-email: ryohidaka <39184410+ryohidaka@users.noreply.github.com>
License: MIT License
License-File: LICENSE
Keywords: japan,japanese,sqlite,zaim
Requires-Python: >=3.8
Requires-Dist: pandas>=2.2.2
Requires-Dist: pyzaim>=1.1.0
Requires-Dist: sqlalchemy>=2.0.31
Requires-Dist: tqdm>=4.66.2
